djipsecure/__init__.py
djipsecure/admin.py
djipsecure/apps.py
djipsecure/middleware.py
djipsecure/models.py
djipsecure/tests.py
djipsecure/views.py
djipsecure/migrations/0001_initial.py
djipsecure/migrations/__init__.py
djipsecure-1.0.2.dist-info/LICENSE
djipsecure-1.0.2.dist-info/METADATA
djipsecure-1.0.2.dist-info/WHEEL
djipsecure-1.0.2.dist-info/top_level.txt
djipsecure-1.0.2.dist-info/RECORD
