Metadata-Version: 2.1
Name: djipsecure
Version: 1.0.2
Summary: Django IP Secure
Home-page: UNKNOWN
License: MIT
Platform: UNKNOWN
Requires-Python: >=3.8.13
License-File: LICENSE
Requires-Dist: Django (>=4.1.5)
